rbtree_py-0.1.4.dist-info/licenses/LICENSE
redblacktree/__init__.py
redblacktree/tree.py
rbtree_py-0.1.4.dist-info/METADATA
rbtree_py-0.1.4.dist-info/WHEEL
rbtree_py-0.1.4.dist-info/top_level.txt
rbtree_py-0.1.4.dist-info/RECORD
