Metadata-Version: 2.4
Name: rbtree-py
Version: 0.1.4
Summary: A Python implementation of a Red-Black Tree data structure.
Author-email: "richard.mychan" <richard.mychan@gmail.com>
License: MIT License
Project-URL: Homepage, https://github.com/manyan-chan/rbtree-py
Project-URL: Repository, https://github.com/manyan-chan/rbtree-py
Keywords: red-black tree,rbtree,binary search tree,bst,data structure,balanced tree
Classifier: Programming Language :: Python :: 3
Classifier: Programming Language :: Python :: 3.8
Classifier: Programming Language :: Python :: 3.9
Classifier: Programming Language :: Python :: 3.10
Classifier: Programming Language :: Python :: 3.11
Classifier: Programming Language :: Python :: 3.12
Classifier: License :: OSI Approved :: MIT License
Classifier: Operating System :: OS Independent
Classifier: Development Status :: 4 - Beta
Classifier: Intended Audience :: Developers
Classifier: Topic :: Software Development :: Libraries :: Python Modules
Classifier: Topic :: Scientific/Engineering :: Information Analysis
Requires-Python: >=3.8
License-File: LICENSE
Provides-Extra: test
Requires-Dist: pytest>=7.0; extra == "test"
Requires-Dist: pytest-cov; extra == "test"
Dynamic: license-file
